CHANGELOG.md
coverage_plot/__init__.py
coverage_plot/cli.py
coverage_plot/fake_implementations.py
coverage_plot/git_changes.py
coverage_plot/importance_filesize.py
coverage_plot/importance_interface.py
coverage_plot/importance_recency.py
coverage_plot/plot.py
coverage_plot-0.3.2.dist-info/METADATA
coverage_plot-0.3.2.dist-info/WHEEL
coverage_plot-0.3.2.dist-info/entry_points.txt
coverage_plot-0.3.2.dist-info/RECORD
