Metadata-Version: 2.1
Name: coverage-plot
Version: 0.3.2
Summary: Library to plot Python code coverage results
Home-page: https://github.com/imankulov/coverage-plot
License: MIT
Author: Roman Imankulov
Author-email: roman.imankulov@gmail.com
Requires-Python: >=3.8.1,<4.0.0
Classifier: Intended Audience :: Developers
Classifier: License :: OSI Approved :: MIT License
Classifier: Natural Language :: English
Classifier: Programming Language :: Python :: 3
Classifier: Programming Language :: Python :: 3.9
Classifier: Programming Language :: Python :: 3.10
Classifier: Programming Language :: Python :: 3.11
Classifier: Programming Language :: Python :: 3
Classifier: Programming Language :: Python :: 3.10
Classifier: Programming Language :: Python :: 3.11
Classifier: Programming Language :: Python :: 3.8
Classifier: Programming Language :: Python :: 3.9
Provides-Extra: docs
Requires-Dist: attrs (>=21.1.0)
Requires-Dist: click (>=8.1.2,<9.0.0)
Requires-Dist: pandas (>=1.0.5,<2.0.0)
Requires-Dist: plotly (>=5,<6)
Requires-Dist: pydriller (>=1.15.2,<2.0.0)
Requires-Dist: sphinx (>=3,<4) ; extra == "docs"
Project-URL: Repository, https://github.com/imankulov/coverage-plot
